accessibility/__init__.py
accessibility/admin.py
accessibility/apps.py
accessibility/context_processors.py
accessibility/forms.py
accessibility/models.py
accessibility/tests.py
accessibility/urls.py
accessibility/views.py
accessibility/migrations/0001_initial.py
accessibility/migrations/0002_alter_allinoneaccessibility_options.py
accessibility/migrations/0003_alter_allinoneaccessibility_aioa_place.py
accessibility/migrations/__init__.py
accessibility/static/admin/css/aioa_admin.css
accessibility/static/admin/js/aioa_accessibility.js
accessibility/static/admin/js/aioa_icon_sync.js
accessibility/templates/home.html
fein_cms_all_in_one_accessibility/__init__.py
fein_cms_all_in_one_accessibility/asgi.py
fein_cms_all_in_one_accessibility/settings.py
fein_cms_all_in_one_accessibility/urls.py
fein_cms_all_in_one_accessibility/wsgi.py
feincms_all_in_one_accessibility-1.0.1.dist-info/licenses/LICENSE
feincms_all_in_one_accessibility-1.0.1.dist-info/METADATA
feincms_all_in_one_accessibility-1.0.1.dist-info/WHEEL
feincms_all_in_one_accessibility-1.0.1.dist-info/top_level.txt
feincms_all_in_one_accessibility-1.0.1.dist-info/RECORD
