Metadata-Version: 2.4
Name: feincms-all-in-one-accessibility
Version: 1.0.1
Summary: Website accessibility widget for improving WCAG 2.0, 2.1, 2.2 and ADA compliance!
Home-page: https://www.skynettechnologies.com
Author: Skynet Technologies USA LLC
Author-email: developer3@skynettechnologies.com
License: MIT
Classifier: Environment :: Web Environment
Classifier: Framework :: Django
Classifier: Intended Audience :: Developers
Classifier: License :: OSI Approved :: MIT License
Classifier: Operating System :: OS Independent
Classifier: Programming Language :: Python
Classifier: Programming Language :: Python :: 3.11
Classifier: Topic :: Internet :: WWW/HTTP
Classifier: Topic :: Internet :: WWW/HTTP :: Dynamic Content
License-File: LICENSE
Requires-Dist: FeinCMS<=25.5.1,>=22.0.0
Requires-Dist: requests
Dynamic: description-content-type
Dynamic: license-file
